fairy_subtitle/__init__.py
fairy_subtitle/block.py
fairy_subtitle/exceptions.py
fairy_subtitle/models.py
fairy_subtitle/parsers.py
fairy_subtitle/subtitle.py
fairy_subtitle-1.1.0.dist-info/licenses/LICENSE
fairy_subtitle-1.1.0.dist-info/METADATA
fairy_subtitle-1.1.0.dist-info/WHEEL
fairy_subtitle-1.1.0.dist-info/top_level.txt
fairy_subtitle-1.1.0.dist-info/RECORD
