Metadata-Version: 2.4
Name: fairy-subtitle
Version: 1.1.0
Summary: A simple Python subtitle parsing library
Author-email: baby2016 <2185823427@qq.com>
Project-URL: Homepage, https://github.com/baby2016/fairy-subtitle
Project-URL: Bug Tracker, https://github.com/baby2016/fairy-subtitle/issues
Classifier: Programming Language :: Python :: 3
Classifier: Programming Language :: Python :: 3.9
Classifier: Programming Language :: Python :: 3.10
Classifier: Programming Language :: Python :: 3.11
Classifier: Programming Language :: Python :: 3.12
Classifier: Programming Language :: Python :: 3.13
Classifier: License :: OSI Approved :: MIT License
Classifier: Operating System :: OS Independent
Classifier: Topic :: Multimedia :: Video :: Display
Classifier: Topic :: Text Processing :: Filters
Requires-Python: >=3.9
License-File: LICENSE
Dynamic: license-file
